{
  "parent": "minecraft:recipes/root",
  "criteria": {
    "has_crystal_niotic_armor": {
      "conditions": {
        "items": [
          {
            "items": "resource_armadillo:crystal_niotic_scute"
          }
        ]
      },
      "trigger": "minecraft:inventory_changed"
    },
    "has_the_recipe": {
      "conditions": {
        "recipe": "resource_armadillo:crystal_niotic_armor_crafted_from_crystal_niotic_scute"
      },
      "trigger": "minecraft:recipe_unlocked"
    }
  },
  "requirements": [
    [
      "has_the_recipe",
      "has_crystal_niotic_armor"
    ]
  ],
  "rewards": {
    "recipes": [
      "resource_armadillo:crystal_niotic_armor_crafted_from_crystal_niotic_scute"
    ]
  }
}